Metadata-Version: 2.1
Name: pdf-ocr-txt
Version: 0.5.0
Summary: Tool to extract and store sentence embeddings to a fast and scalable vector db
Home-page: https://github.com/ptarau/pdf_ocr_txt.git
Author: Paul Tarau
Author-email: paul.tarau@gmail.com
License: MIT
License-File: LICENSE
